abstracting_machine/__init__.py
abstracting_machine-0.0.1.dist-info/licenses/LICENSE
abstracting_machine-0.0.1.dist-info/METADATA
abstracting_machine-0.0.1.dist-info/WHEEL
abstracting_machine-0.0.1.dist-info/top_level.txt
abstracting_machine-0.0.1.dist-info/RECORD
